hesperidescli/client.py
hesperidescli/hesperidescli.py
hesperidescli/utils.py
hesperidescli/__init__.py
hesperidescli/__version__.py
hesperidescli/applications/applications.py
hesperidescli/applications/__init__.py
hesperidescli/applications/platforms/platforms.py
hesperidescli/applications/platforms/__init__.py
hesperidescli/applications/platforms/properties/properties.py
hesperidescli/applications/platforms/properties/__init__.py
hesperidescli/applications/platforms/snapshots/snapshots.py
hesperidescli/applications/platforms/snapshots/__init__.py
hesperidescli/cache/cache.py
hesperidescli/cache/__init__.py
hesperidescli/configure/configfile.py
hesperidescli/configure/configure.py
hesperidescli/configure/reader.py
hesperidescli/configure/writer.py
hesperidescli/configure/__init__.py
hesperidescli/events/events.py
hesperidescli/events/__init__.py
hesperidescli/feedback/feedback.py
hesperidescli/feedback/__init__.py
hesperidescli/files/files.py
hesperidescli/files/__init__.py
hesperidescli/indexation/indexation.py
hesperidescli/indexation/__init__.py
hesperidescli/modules/modules.py
hesperidescli/modules/__init__.py
hesperidescli/stats/stats.py
hesperidescli/stats/__init__.py
hesperidescli/templates/templates.py
hesperidescli/templates/__init__.py
hesperidescli/users/users.py
hesperidescli/users/__init__.py
hesperidescli/versions/versions.py
hesperidescli/versions/__init__.py
hesperides_cli-0.2.1.dist-info/DESCRIPTION.rst
hesperides_cli-0.2.1.dist-info/entry_points.txt
hesperides_cli-0.2.1.dist-info/METADATA
hesperides_cli-0.2.1.dist-info/metadata.json
hesperides_cli-0.2.1.dist-info/RECORD
hesperides_cli-0.2.1.dist-info/top_level.txt
hesperides_cli-0.2.1.dist-info/WHEEL
