Metadata-Version: 2.0
Name: hesperides-cli
Version: 0.2.1
Summary: Command Line Interface for Hesperides
Home-page: https://github.com/victorsalaun/hesperides-cli
Author: Victor SALAUN
Author-email: victor.salaun@gmail.com
License: GPLv3
Platform: UNKNOWN
Classifier: Environment :: Console
Classifier: License :: OSI Approved :: GNU General Public License v3 (GPLv3)
Classifier: Programming Language :: Python
Classifier: Programming Language :: Python :: 3.4
Classifier: Programming Language :: Python :: 3.5
Classifier: Programming Language :: Python :: 3.6
Classifier: Programming Language :: Python :: Implementation :: CPython
Classifier: Programming Language :: Python :: Implementation :: PyPy
Requires-Dist: click
